{
  "kind": "collectionType",
  "collectionName": "carts",
  "info": {
    "singularName": "cart",
    "pluralName": "carts",
    "displayName": "Cart",
    "description": ""
  },
  "options": {
    "draftAndPublish": false
  },
  "pluginOptions": {},
  "attributes": {
    "title": {
      "type": "string"
    },
    "discountedPrice": {
      "type": "decimal"
    },
    "quantity": {
      "type": "decimal",
      "default": 1
    },
    "img": {
      "type": "media",
      "multiple": false,
      "required": false,
      "allowedTypes": [
        "images",
        "files",
        "videos",
        "audios"
      ]
    }
  }
}
